[
  {
    "Dictionary": {
      "Before": {
        "Abst": 0,
        "CTScore": 3,
        "Data": 0,
        "Flow": 2,
        "Logi": 0,
        "Para": 0,
        "Sync": 0,
        "User": 1
      },
      "Distance": 3,
      "Reach": 18
    },
    "Count": 1
  },
  {
    "Dictionary": {
      "Before": {
        "Abst": 0,
        "CTScore": 3,
        "Data": 0,
        "Flow": 1,
        "Logi": 0,
        "Para": 0,
        "Sync": 1,
        "User": 1
      },
      "Distance": 1,
      "Reach": 17
    },
    "Count": 1
  },
  {
    "Dictionary": {
      "Before": {
        "Abst": 0,
        "CTScore": 3,
        "Data": 0,
        "Flow": 2,
        "Logi": 0,
        "Para": 0,
        "Sync": 0,
        "User": 1
      },
      "Distance": 1,
      "Reach": 19
    },
    "Count": 1
  },
  {
    "Dictionary": {
      "Before": {
        "Abst": 0,
        "CTScore": 3,
        "Data": 1,
        "Flow": 1,
        "Logi": 0,
        "Para": 0,
        "Sync": 0,
        "User": 1
      },
      "Distance": 1,
      "Reach": 16
    },
    "Count": 1
  },
  {
    "Dictionary": {
      "Before": {
        "Abst": 0,
        "CTScore": 3,
        "Data": 1,
        "Flow": 1,
        "Logi": 0,
        "Para": 0,
        "Sync": 0,
        "User": 1
      },
      "Distance": 7,
      "Reach": 15
    },
    "Count": 1
  }
]